Locker_Project/CMD_Process.py
Locker_Project/CMD_ScanInput.py
Locker_Project/CMD_Thread.py
Locker_Project/Func.py
Locker_Project/MyTask_Finger.py
Locker_Project/MyTask_Tag.py
Locker_Project/Test_Send_Dta.py
Locker_Project/__init__.py
Locker_Project/adafruit_fingerprint.py
Locker_Project/mian.py
Locker_Project/test.py
Locker_Project-1.1.3.dist-info/LICENSE
Locker_Project-1.1.3.dist-info/METADATA
Locker_Project-1.1.3.dist-info/WHEEL
Locker_Project-1.1.3.dist-info/top_level.txt
Locker_Project-1.1.3.dist-info/RECORD
