Metadata-Version: 2.1
Name: Locker-Project
Version: 1.1.3
Summary: Locker_Project Load
Home-page: https://github.com/huynhquoc1990/Locker_Project.git
Author: Huỳnh Tấn Quốc
Author-email: huynhquoc1990@gamil.com
License: MIT
Platform: UNKNOWN
Classifier: Programming Language :: Python :: 3
Classifier: License :: OSI Approved :: MIT License
Classifier: Operating System :: OS Independent
